MANIFEST.in
README.rst
setup.cfg
setup.py
src/systemd.py
src/systemd.egg-info/PKG-INFO
src/systemd.egg-info/SOURCES.txt
src/systemd.egg-info/dependency_links.txt
src/systemd.egg-info/requires.txt
src/systemd.egg-info/top_level.txt