Metadata-Version: 1.1
Name: systemd
Version: 0.17.1
Summary: systemd wrapper in Cython
Home-page: http://github.com/mosquito/cysystemd
Author: UNKNOWN
Author-email: UNKNOWN
License: Apache
Keywords: systemd,python,daemon,sd_notify,cython
Platform: POSIX
Provides: systemd
